fitbenchmarking/__init__.py
fitbenchmarking/__main__.py
fitbenchmarking/benchmark_problems/NIST/average_difficulty/ENSO.dat
fitbenchmarking/benchmark_problems/NIST/average_difficulty/Gauss3.dat
fitbenchmarking/benchmark_problems/NIST/average_difficulty/Hahn1.dat
fitbenchmarking/benchmark_problems/NIST/average_difficulty/Kirby2.dat
fitbenchmarking/benchmark_problems/NIST/average_difficulty/Lanczos1.dat
fitbenchmarking/benchmark_problems/NIST/average_difficulty/Lanczos2.dat
fitbenchmarking/benchmark_problems/NIST/average_difficulty/META.txt
fitbenchmarking/benchmark_problems/NIST/average_difficulty/MGH17.dat
fitbenchmarking/benchmark_problems/NIST/average_difficulty/Misra1c.dat
fitbenchmarking/benchmark_problems/NIST/average_difficulty/Misra1d.dat
fitbenchmarking/benchmark_problems/NIST/average_difficulty/data_files/ENSO.hes
fitbenchmarking/benchmark_problems/NIST/average_difficulty/data_files/ENSO.jac
fitbenchmarking/benchmark_problems/NIST/average_difficulty/data_files/Gauss3.hes
fitbenchmarking/benchmark_problems/NIST/average_difficulty/data_files/Gauss3.jac
fitbenchmarking/benchmark_problems/NIST/average_difficulty/data_files/Hahn1.hes
fitbenchmarking/benchmark_problems/NIST/average_difficulty/data_files/Hahn1.jac
fitbenchmarking/benchmark_problems/NIST/average_difficulty/data_files/Kirby2.hes
fitbenchmarking/benchmark_problems/NIST/average_difficulty/data_files/Kirby2.jac
fitbenchmarking/benchmark_problems/NIST/average_difficulty/data_files/Lanczos1.hes
fitbenchmarking/benchmark_problems/NIST/average_difficulty/data_files/Lanczos1.jac
fitbenchmarking/benchmark_problems/NIST/average_difficulty/data_files/Lanczos2.hes
fitbenchmarking/benchmark_problems/NIST/average_difficulty/data_files/Lanczos2.jac
fitbenchmarking/benchmark_problems/NIST/average_difficulty/data_files/MGH17.hes
fitbenchmarking/benchmark_problems/NIST/average_difficulty/data_files/MGH17.jac
fitbenchmarking/benchmark_problems/NIST/average_difficulty/data_files/Misra1c.hes
fitbenchmarking-1.3.0.dist-info/METADATA
fitbenchmarking-1.3.0.dist-info/WHEEL
fitbenchmarking-1.3.0.dist-info/entry_points.txt
fitbenchmarking-1.3.0.dist-info/licenses/LICENSE.txt
fitbenchmarking-1.3.0.dist-info/RECORD
