Metadata-Version: 2.4
Name: FitBenchmarking
Version: 1.3.0
Summary: FitBenchmarking: A tool for comparing fitting software
Project-URL: Homepage, https://fitbenchmarking.github.io
Project-URL: Documentation, https://fitbenchmarking.readthedocs.io/en/stable
Project-URL: Repository, https://github.com/fitbenchmarking/fitbenchmarking
Project-URL: Release Notes, https://github.com/fitbenchmarking/fitbenchmarking/releases
Project-URL: Issues, https://github.com/fitbenchmarking/fitbenchmarking/issues
Author: FitBenchmarking Team
License-File: LICENSE.txt
Keywords: benchmark,comparison,fitting,least squares,optimisation
Classifier: License :: OSI Approved :: BSD License
Classifier: Operating System :: OS Independent
Classifier: Programming Language :: Python :: 3
Requires-Python: >=3.9.1
Requires-Dist: codecarbon<2.7,>=2.5.1
Requires-Dist: configparser
Requires-Dist: dash
Requires-Dist: docutils
Requires-Dist: jinja2
Requires-Dist: lxml
Requires-Dist: matplotlib>=2.0
Requires-Dist: numpy
Requires-Dist: pandas>=1.3
Requires-Dist: plotly>=5.0.0
Requires-Dist: scipy>=0.18
Requires-Dist: tqdm>=4.60
Provides-Extra: bumps
Requires-Dist: bumps>=0.9.0; extra == 'bumps'
Provides-Extra: dev
Requires-Dist: coverage[toml]>=6.3; extra == 'dev'
Requires-Dist: coveralls; extra == 'dev'
Requires-Dist: iminuit>=2.25.2; extra == 'dev'
Requires-Dist: pandas; extra == 'dev'
Requires-Dist: parameterized; extra == 'dev'
Requires-Dist: pre-commit; extra == 'dev'
Requires-Dist: pytest; extra == 'dev'
Requires-Dist: pytest-cov>=4.0.0; extra == 'dev'
Requires-Dist: ruff; extra == 'dev'
Provides-Extra: dfo
Requires-Dist: dfo-ls; extra == 'dfo'
Provides-Extra: gofit
Requires-Dist: gofit; extra == 'gofit'
Provides-Extra: gradient-free
Requires-Dist: gradient-free-optimizers; extra == 'gradient-free'
Provides-Extra: hogben
Requires-Dist: hogben; extra == 'hogben'
Provides-Extra: levmar
Requires-Dist: levmar; extra == 'levmar'
Provides-Extra: lmfit
Requires-Dist: emcee>=3.1.0; extra == 'lmfit'
Requires-Dist: lmfit; extra == 'lmfit'
Provides-Extra: mantid
Requires-Dist: h5py<3,>=2.10.0; extra == 'mantid'
Requires-Dist: pyyaml>=5.4.1; extra == 'mantid'
Provides-Extra: matlab
Requires-Dist: dill; extra == 'matlab'
Provides-Extra: minuit
Requires-Dist: iminuit>=2.0; extra == 'minuit'
Provides-Extra: nlopt
Requires-Dist: nlopt; extra == 'nlopt'
Provides-Extra: numdifftools
Requires-Dist: numdifftools; extra == 'numdifftools'
Provides-Extra: paramonte
Requires-Dist: paramonte; extra == 'paramonte'
Provides-Extra: sas
Requires-Dist: sasmodels; extra == 'sas'
Requires-Dist: tinycc; (platform_system == 'Windows') and extra == 'sas'
